LICENSE
README.md
setup.py
itmagazines_webscraper/__init__.py
itmagazines_webscraper/web_scraper.py
itmagazines_webscraper.egg-info/PKG-INFO
itmagazines_webscraper.egg-info/SOURCES.txt
itmagazines_webscraper.egg-info/dependency_links.txt
itmagazines_webscraper.egg-info/requires.txt
itmagazines_webscraper.egg-info/top_level.txt