Metadata-Version: 2.1
Name: itmagazines-webscraper
Version: 0.1.0
Summary: WEB Scraper for IT-Magazines.
Home-page: https://github.com/imoni31/itmagazines-webscraper
Author: imoni
Author-email: saito@imoni.net
License: MIT
Platform: UNKNOWN
Classifier: License :: OSI Approved :: MIT License
Classifier: Programming Language :: Python
Classifier: Programming Language :: Python :: 3
Classifier: Programming Language :: Python :: 3.7
Classifier: Programming Language :: Python :: 3.8
Classifier: Programming Language :: Python :: 3.9
Classifier: Programming Language :: Python :: 3.10
Classifier: Programming Language :: Python :: 3.11
Classifier: Programming Language :: Python :: 3 :: Only
Requires-Python: >=3.7
License-File: LICENSE
